README.md
setup.py
inoon_lora_packet/__init__.py
inoon_lora_packet/packet.py
inoon_lora_packet/parser.py
inoon_lora_packet.egg-info/PKG-INFO
inoon_lora_packet.egg-info/SOURCES.txt
inoon_lora_packet.egg-info/dependency_links.txt
inoon_lora_packet.egg-info/entry_points.txt
inoon_lora_packet.egg-info/top_level.txt
inoon_lora_packet/base/base_parser.py
inoon_lora_packet/bsp/accelerometer.py
inoon_lora_packet/v2/__init__.py
inoon_lora_packet/v2/ack.py
inoon_lora_packet/v2/alive.py
inoon_lora_packet/v2/data_log.py
inoon_lora_packet/v2/error.py
inoon_lora_packet/v2/event.py
inoon_lora_packet/v2/notice.py
inoon_lora_packet/v2/parser.py
inoon_lora_packet/v3/__init__.py
inoon_lora_packet/v3/acc_wave.py
inoon_lora_packet/v3/ack.py
inoon_lora_packet/v3/alive.py
inoon_lora_packet/v3/data_log.py
inoon_lora_packet/v3/error.py
inoon_lora_packet/v3/event.py
inoon_lora_packet/v3/inclination.py
inoon_lora_packet/v3/mr_measurement.py
inoon_lora_packet/v3/mr_report.py
inoon_lora_packet/v3/notice.py
inoon_lora_packet/v3/parser.py
inoon_lora_packet/v3/report.py