Metadata-Version: 1.0
Name: inoon-lora-packet
Version: 4.1.0
Summary: LoRa packet parser for Ino-on, Inc.
Home-page: UNKNOWN
Author: Joonkyo Kim
Author-email: jkkim@ino-on.com
License: UNKNOWN
Platform: UNKNOWN
